README.md
setup.cfg
setup.py
pyladins/__init__.py
pyladins.egg-info/PKG-INFO
pyladins.egg-info/SOURCES.txt
pyladins.egg-info/dependency_links.txt
pyladins.egg-info/not-zip-safe
pyladins.egg-info/top_level.txt