Metadata-Version: 1.1
Name: pyladins
Version: 0.1
Summary: Python API for paladins
Home-page: http://github.com/shubhstiws/paladins
Author: Shubhankar Tiwari
Author-email: shubhstiws@gmail.com
License: MIT
Keywords: paladins setuptools development
Platform: UNKNOWN
Classifier: Development Status :: 3 - Alpha
Classifier: Intended Audience :: Developers
Classifier: Topic :: Software Development :: Build Tools
Classifier: License :: OSI Approved :: MIT License
Classifier: Programming Language :: Python :: 3.6
